[
  {
    "id": "Testing_test_2025-08-19_23-11-49",
    "project": "Testing",
    "testName": "test",
    "timestamp": "2025-08-19_23-11-49",
    "reportPath": "/reports/Testing",
    "status": "passed"
  },
  {
    "id": "Project_1_User_Login-2025-08-20_15-52-33",
    "project": "Project_1",
    "testName": "User_Login",
    "timestamp": "2025-08-20_15-52-33",
    "reportPath": "/reports/Project_1",
    "status": "passed"
  },
  {
    "id": "Project_1_User_Login-2025-08-20_15-52-49",
    "project": "Project_1",
    "testName": "User_Login",
    "timestamp": "2025-08-20_15-52-49",
    "reportPath": "/reports/Project_1",
    "status": "passed"
  },
  {
    "id": "Project_1_User_Login-2025-08-20_16-25-41",
    "project": "Project_1",
    "testName": "User_Login",
    "timestamp": "2025-08-20_16-25-41",
    "reportPath": "/reports/Project_1",
    "status": "passed"
  },
  {
    "id": "Project_1_User_Login-2025-08-21_18-37-18",
    "project": "Project_1",
    "testName": "User_Login",
    "timestamp": "2025-08-21_18-37-18",
    "reportPath": "/reports/Project_1",
    "status": "passed"
  },
  {
    "id": "Project_1_Dashboard_Access-2025-08-21_23-58-00",
    "project": "Project_1",
    "testName": "Dashboard_Access",
    "timestamp": "2025-08-21_23-58-00",
    "reportPath": "/reports/Project_1",
    "status": "failed"
  },
  {
    "id": "Project_1_Dashboard_Access-2025-08-21_23-59-24",
    "project": "Project_1",
    "testName": "Dashboard_Access",
    "timestamp": "2025-08-21_23-59-24",
    "reportPath": "/reports/Project_1",
    "status": "failed"
  },
  {
    "id": "Project_1_Dashboard_Access-2025-08-22_00-01-07",
    "project": "Project_1",
    "testName": "Dashboard_Access",
    "timestamp": "2025-08-22_00-01-07",
    "reportPath": "/reports/Project_1",
    "status": "failed"
  },
  {
    "id": "Project_1_Dashboard_Access-2025-08-22_00-16-44",
    "project": "Project_1",
    "testName": "Dashboard_Access",
    "timestamp": "2025-08-22_00-16-44",
    "reportPath": "/reports/Project_1",
    "status": "failed"
  },
  {
    "id": "Project_1_Dashboard_Access-2025-08-22_00-17-45",
    "project": "Project_1",
    "testName": "Dashboard_Access",
    "timestamp": "2025-08-22_00-17-45",
    "reportPath": "/reports/Project_1",
    "status": "failed"
  },
  {
    "id": "Project_1_User_Login-2025-08-22_00-19-14",
    "project": "Project_1",
    "testName": "User_Login",
    "timestamp": "2025-08-22_00-19-14",
    "reportPath": "/reports/Project_1",
    "status": "failed"
  },
  {
    "id": "Project_1_User_Login-2025-08-22_00-20-06",
    "project": "Project_1",
    "testName": "User_Login",
    "timestamp": "2025-08-22_00-20-06",
    "reportPath": "/reports/Project_1",
    "status": "passed"
  },
  {
    "id": "Project_1_Dashboard_Access-2025-08-25_11-20-40",
    "project": "Project_1",
    "testName": "Dashboard_Access",
    "timestamp": "2025-08-25_11-20-40",
    "reportPath": "/reports/Project_1",
    "status": "failed"
  }
]